  4           0 LOAD_CONST               1 ('')
              2 STORE_FAST               0 (f)				//f = ''

  5           4 LOAD_CONST               2 ('rwhxi}eomr\\^`Y')
              6 STORE_FAST               1 (a)				//a = rwhxi}eomr\\^`Y

  6           8 LOAD_CONST               3 ('f]XdThbQd^TYL&\x13g')
             10 STORE_FAST               2 (z)				//z = f]XdThbQd^TYL&\x13g	

  7          12 LOAD_FAST                1 (a)
             14 LOAD_FAST                2 (z)
             16 BINARY_ADD
             18 STORE_FAST               1 (a)		//a='rwhxi}eomr\\^`Yf]XdThbQd^TYL&\x13g'

  8          20 LOAD_GLOBAL              0 (enumerate) 
             22 LOAD_FAST                1 (a)		//enum(a)=['rwhxi}eomr\\^`Y', 'f]XdThbQd^TYL&\x13g']
             24 CALL_FUNCTION            1
             26 GET_ITER			   	//iter(a)
        >>   28 FOR_ITER                48 (to 78) 	//iter(a).next(), nhảy đến 78 nếu không next()
             30 UNPACK_SEQUENCE          2
             32 STORE_FAST               3 (i) 		//i = iter(a).next()
             34 STORE_FAST               4 (b) 		//b = a[i]

  9          36 LOAD_GLOBAL              1 (ord)
             38 LOAD_FAST                4 (b)
             40 CALL_FUNCTION            1 		//ord(b)
             42 STORE_FAST               5 (c)		//c = ord(b)

 10          44 LOAD_FAST                5 (c)
             46 LOAD_CONST               4 (7)
             48 BINARY_SUBTRACT				//c-7
             50 STORE_FAST               5 (c)		

 11          52 LOAD_FAST                5 (c)
             54 LOAD_FAST                3 (i)
             56 BINARY_ADD				//c + i
             58 STORE_FAST               5 (c)		//c = c + i

 12          60 LOAD_GLOBAL              2 (chr)
             62 LOAD_FAST                5 (c)
             64 CALL_FUNCTION            1		//chr(c)
             66 STORE_FAST               5 (c)		//c = chr(c)

 13          68 LOAD_FAST                0 (f)
             70 LOAD_FAST                5 (c)
             72 INPLACE_ADD				//f + c
             74 STORE_FAST               0 (f)		//f = f + c
             76 JUMP_ABSOLUTE           28

 14     >>   78 LOAD_GLOBAL              3 (print)
             80 LOAD_FAST                0 (f)		//==>f
             82 CALL_FUNCTION            1
             84 POP_TOP
             86 LOAD_CONST               0 (None)
             88 RETURN_VALUE
